brem/AsyncCopyOverSSH.py
brem/__init__.py
brem/brem.py
brem/version.py
brem/ui/RemoteFileDialog.py
brem/ui/RemoteServerSettingDialog.py
brem/ui/__init__.py
brem-1.1.0.dist-info/LICENSE
brem-1.1.0.dist-info/METADATA
brem-1.1.0.dist-info/WHEEL
brem-1.1.0.dist-info/top_level.txt
brem-1.1.0.dist-info/RECORD
