Metadata-Version: 2.1
Name: brem
Version: 1.1.0
Summary: Basic Remote Execution Manager
Home-page: https://github.com/paskino/brem
Author: Alin M Elena, Edoardo Pasca
Author-email: alin-marin.elena@stfc.ac.uk, edoardo.pasca@stfc.ac.uk
License: BSD-3
Platform: UNKNOWN
Classifier: Development Status :: 4 - Beta
Classifier: Programming Language :: Python :: 3
Classifier: License :: OSI Approved :: BSD License
Classifier: Operating System :: OS Independent
Classifier: Topic :: Scientific/Engineering :: Physics
License-File: LICENSE
Requires-Dist: paramiko (>=2.7.2)
Requires-Dist: eqt
